odoo/addons/maintenance_equipment_sequence/README.rst
odoo/addons/maintenance_equipment_sequence/__init__.py
odoo/addons/maintenance_equipment_sequence/__manifest__.py
odoo/addons/maintenance_equipment_sequence/i18n/es.po
odoo/addons/maintenance_equipment_sequence/i18n/it.po
odoo/addons/maintenance_equipment_sequence/i18n/maintenance_equipment_sequence.pot
odoo/addons/maintenance_equipment_sequence/models/__init__.py
odoo/addons/maintenance_equipment_sequence/models/maintenance.py
odoo/addons/maintenance_equipment_sequence/readme/CONTRIBUTORS.md
odoo/addons/maintenance_equipment_sequence/readme/DESCRIPTION.md
odoo/addons/maintenance_equipment_sequence/static/description/icon.png
odoo/addons/maintenance_equipment_sequence/static/description/index.html
odoo/addons/maintenance_equipment_sequence/tests/__init__.py
odoo/addons/maintenance_equipment_sequence/tests/test_maintenance_equipment_sequence.py
odoo/addons/maintenance_equipment_sequence/views/maintenance_views.xml
odoo_addon_maintenance_equipment_sequence-18.0.1.0.0.2.dist-info/METADATA
odoo_addon_maintenance_equipment_sequence-18.0.1.0.0.2.dist-info/WHEEL
odoo_addon_maintenance_equipment_sequence-18.0.1.0.0.2.dist-info/top_level.txt
odoo_addon_maintenance_equipment_sequence-18.0.1.0.0.2.dist-info/RECORD
